timewizard/__init__.py
timewizard/perievent.py
timewizard/util.py
timewizard/allenbrainobs/__init__.py
timewizard/allenbrainobs/obs_utils.py
timewizard-0.1.2.dist-info/METADATA
timewizard-0.1.2.dist-info/WHEEL
timewizard-0.1.2.dist-info/top_level.txt
timewizard-0.1.2.dist-info/RECORD
