Metadata-Version: 2.1
Name: timewizard
Version: 0.1.2
Summary: Your timeseries woes will magically disappear
Home-page: https://github.com/jonahpearl/timewizard
Author: Jonah Pearl
Author-email: jonahpearl@g.harvard.edu
License: MIT or Allen Institute Software License
Project-URL: Issue Tracker, https://github.com/jonahpearl/timewizard/issues
Classifier: Development Status :: 1 - Planning
Classifier: Intended Audience :: Science/Research
Classifier: License :: OSI Approved :: MIT License
Classifier: Operating System :: Unix
Classifier: Operating System :: POSIX
Classifier: Operating System :: Microsoft :: Windows
Classifier: Programming Language :: Python :: 3
Classifier: Topic :: Scientific/Engineering :: Image Processing
Requires-Python: >=3.7
Requires-Dist: numpy
Requires-Dist: scipy
Requires-Dist: fastcluster
Requires-Dist: pandas
Requires-Dist: matplotlib
